{
  "title": "蝶と薔薇の罪と罰",
  "artist": "Tandess (GUMI×さとうささら)",
  "difficulty": "NORMAL",
  "bpm": 92,
  "audioFile": "songs/hero_short.mp3",
  "offset": 0,
  "notes": [
    {
      "lane": 4,
      "time": 1625,
      "type": "tap"
    },
    {
      "lane": 4,
      "time": 2275,
      "type": "tap"
    },
    {
      "lane": 3,
      "time": 2948,
      "type": "tap"
    },
    {
      "lane": 3,
      "time": 3599,
      "type": "flick"
    },
    {
      "lane": 4,
      "time": 3599,
      "type": "tap"
    },
    {
      "lane": 4,
      "time": 3947,
      "type": "tap"
    },
    {
      "lane": 5,
      "time": 4272,
      "type": "tap"
    },
    {
      "lane": 3,
      "time": 4922,
      "type": "flick"
    },
    {
      "lane": 4,
      "time": 4922,
      "type": "tap"
    },
    {
      "lane": 3,
      "time": 5596,
      "type": "tap"
    },
    {
      "lane": 4,
      "time": 6246,
      "type": "tap"
    },
    {
      "lane": 5,
      "time": 6896,
      "type": "tap"
    },
    {
      "lane": 4,
      "time": 7546,
      "type": "tap"
    },
    {
      "lane": 3,
      "time": 8219,
      "type": "tap"
    },
    {
      "lane": 3,
      "time": 8870,
      "type": "flick"
    },
    {
      "lane": 4,
      "time": 8870,
      "type": "tap"
    },
    {
      "lane": 5,
      "time": 9520,
      "type": "tap"
    },
    {
      "lane": 4,
      "time": 9891,
      "type": "tap"
    },
    {
      "lane": 4,
      "time": 10193,
      "type": "tap"
    },
    {
      "lane": 3,
      "time": 10704,
      "type": "tap"
    },
    {
      "lane": 3,
      "time": 11192,
      "type": "tap"
    },
    {
      "lane": 4,
      "time": 11865,
      "type": "tap"
    },
    {
      "lane": 3,
      "time": 12515,
      "type": "tap"
    },
    {
      "lane": 3,
      "time": 13165,
      "type": "tap"
    },
    {
      "lane": 3,
      "time": 13815,
      "type": "tap"
    },
    {
      "lane": 4,
      "time": 14489,
      "type": "tap"
    },
    {
      "lane": 4,
      "time": 15162,
      "type": "tap"
    },
    {
      "lane": 3,
      "time": 15812,
      "type": "tap"
    },
    {
      "lane": 4,
      "time": 16486,
      "type": "tap"
    },
    {
      "lane": 3,
      "time": 17136,
      "type": "tap"
    },
    {
      "lane": 3,
      "time": 17786,
      "type": "tap"
    },
    {
      "lane": 4,
      "time": 18436,
      "type": "tap"
    },
    {
      "lane": 4,
      "time": 19110,
      "type": "tap"
    },
    {
      "lane": 4,
      "time": 19760,
      "type": "tap"
    },
    {
      "lane": 4,
      "time": 20433,
      "type": "tap"
    },
    {
      "lane": 4,
      "time": 21083,
      "type": "tap"
    },
    {
      "lane": 4,
      "time": 21757,
      "type": "tap"
    },
    {
      "lane": 4,
      "time": 22407,
      "type": "tap"
    },
    {
      "lane": 4,
      "time": 23057,
      "type": "tap"
    },
    {
      "lane": 4,
      "time": 23730,
      "type": "tap"
    },
    {
      "lane": 4,
      "time": 24380,
      "type": "tap"
    },
    {
      "lane": 4,
      "time": 25054,
      "type": "tap"
    },
    {
      "lane": 4,
      "time": 25704,
      "type": "tap"
    },
    {
      "lane": 3,
      "time": 26354,
      "type": "tap"
    },
    {
      "lane": 4,
      "time": 27028,
      "type": "tap"
    },
    {
      "lane": 4,
      "time": 27678,
      "type": "tap"
    },
    {
      "lane": 4,
      "time": 28351,
      "type": "tap"
    },
    {
      "lane": 4,
      "time": 29001,
      "type": "tap"
    },
    {
      "lane": 4,
      "time": 29651,
      "type": "tap"
    },
    {
      "lane": 4,
      "time": 30325,
      "type": "tap"
    },
    {
      "lane": 4,
      "time": 30975,
      "type": "tap"
    },
    {
      "lane": 3,
      "time": 31625,
      "type": "tap"
    },
    {
      "lane": 5,
      "time": 32298,
      "type": "tap"
    },
    {
      "lane": 3,
      "time": 32461,
      "type": "tap"
    },
    {
      "lane": 3,
      "time": 32949,
      "type": "tap"
    },
    {
      "lane": 4,
      "time": 33622,
      "type": "tap"
    },
    {
      "lane": 4,
      "time": 34272,
      "type": "tap"
    },
    {
      "lane": 3,
      "time": 34922,
      "type": "tap"
    },
    {
      "lane": 4,
      "time": 35596,
      "type": "tap"
    },
    {
      "lane": 4,
      "time": 36246,
      "type": "tap"
    },
    {
      "lane": 4,
      "time": 36919,
      "type": "tap"
    },
    {
      "lane": 4,
      "time": 37569,
      "type": "tap"
    },
    {
      "lane": 3,
      "time": 38220,
      "type": "tap"
    },
    {
      "lane": 3,
      "time": 38730,
      "type": "tap"
    },
    {
      "lane": 4,
      "time": 38893,
      "type": "tap"
    },
    {
      "lane": 2,
      "time": 39218,
      "type": "tap"
    },
    {
      "lane": 4,
      "time": 39543,
      "type": "tap"
    },
    {
      "lane": 4,
      "time": 40216,
      "type": "tap"
    },
    {
      "lane": 3,
      "time": 40867,
      "type": "tap"
    },
    {
      "lane": 2,
      "time": 41029,
      "type": "tap"
    },
    {
      "lane": 2,
      "time": 41354,
      "type": "tap"
    },
    {
      "lane": 3,
      "time": 41517,
      "type": "tap"
    },
    {
      "lane": 4,
      "time": 42190,
      "type": "tap"
    },
    {
      "lane": 4,
      "time": 42840,
      "type": "tap"
    },
    {
      "lane": 3,
      "time": 43514,
      "type": "tap"
    },
    {
      "lane": 4,
      "time": 44164,
      "type": "tap"
    },
    {
      "lane": 3,
      "time": 44814,
      "type": "tap"
    },
    {
      "lane": 4,
      "time": 45487,
      "type": "tap"
    },
    {
      "lane": 4,
      "time": 46138,
      "type": "tap"
    },
    {
      "lane": 3,
      "time": 46811,
      "type": "tap"
    },
    {
      "lane": 4,
      "time": 47461,
      "type": "tap"
    },
    {
      "lane": 4,
      "time": 48134,
      "type": "tap"
    },
    {
      "lane": 4,
      "time": 48785,
      "type": "tap"
    },
    {
      "lane": 4,
      "time": 49435,
      "type": "tap"
    },
    {
      "lane": 4,
      "time": 50108,
      "type": "tap"
    },
    {
      "lane": 3,
      "time": 50758,
      "type": "tap"
    },
    {
      "lane": 3,
      "time": 51408,
      "type": "tap"
    },
    {
      "lane": 3,
      "time": 52082,
      "type": "tap"
    },
    {
      "lane": 3,
      "time": 52732,
      "type": "tap"
    },
    {
      "lane": 4,
      "time": 53405,
      "type": "tap"
    },
    {
      "lane": 4,
      "time": 54056,
      "type": "tap"
    },
    {
      "lane": 3,
      "time": 54706,
      "type": "tap"
    },
    {
      "lane": 1,
      "time": 55379,
      "type": "tap"
    },
    {
      "lane": 4,
      "time": 55379,
      "type": "tap"
    },
    {
      "lane": 3,
      "time": 56029,
      "type": "tap"
    },
    {
      "lane": 3,
      "time": 56679,
      "type": "tap"
    },
    {
      "lane": 4,
      "time": 57353,
      "type": "tap"
    },
    {
      "lane": 4,
      "time": 58003,
      "type": "tap"
    },
    {
      "lane": 3,
      "time": 58514,
      "type": "tap"
    },
    {
      "lane": 3,
      "time": 59164,
      "type": "tap"
    },
    {
      "lane": 3,
      "time": 59698,
      "type": "tap"
    },
    {
      "lane": 2,
      "time": 60279,
      "type": "tap"
    },
    {
      "lane": 3,
      "time": 60279,
      "type": "tap"
    },
    {
      "lane": 3,
      "time": 60859,
      "type": "tap"
    },
    {
      "lane": 4,
      "time": 61440,
      "type": "tap"
    },
    {
      "lane": 3,
      "time": 62020,
      "type": "tap"
    },
    {
      "lane": 3,
      "time": 62345,
      "type": "tap"
    },
    {
      "lane": 3,
      "time": 62670,
      "type": "tap"
    },
    {
      "lane": 4,
      "time": 63320,
      "type": "tap"
    },
    {
      "lane": 4,
      "time": 63994,
      "type": "tap"
    },
    {
      "lane": 3,
      "time": 64644,
      "type": "tap"
    },
    {
      "lane": 2,
      "time": 64969,
      "type": "tap"
    },
    {
      "lane": 2,
      "time": 65294,
      "type": "tap"
    },
    {
      "lane": 3,
      "time": 65294,
      "type": "tap"
    },
    {
      "lane": 4,
      "time": 65967,
      "type": "tap"
    },
    {
      "lane": 3,
      "time": 66618,
      "type": "tap"
    },
    {
      "lane": 3,
      "time": 67291,
      "type": "tap"
    },
    {
      "lane": 4,
      "time": 67941,
      "type": "tap"
    },
    {
      "lane": 3,
      "time": 68614,
      "type": "tap"
    },
    {
      "lane": 4,
      "time": 69265,
      "type": "tap"
    },
    {
      "lane": 3,
      "time": 69590,
      "type": "tap"
    },
    {
      "lane": 4,
      "time": 69915,
      "type": "tap"
    },
    {
      "lane": 2,
      "time": 70588,
      "type": "tap"
    },
    {
      "lane": 3,
      "time": 70588,
      "type": "tap"
    },
    {
      "lane": 3,
      "time": 71238,
      "type": "tap"
    },
    {
      "lane": 3,
      "time": 71912,
      "type": "tap"
    },
    {
      "lane": 4,
      "time": 72562,
      "type": "tap"
    },
    {
      "lane": 3,
      "time": 72887,
      "type": "tap"
    },
    {
      "lane": 3,
      "time": 73212,
      "type": "tap"
    },
    {
      "lane": 3,
      "time": 73885,
      "type": "tap"
    },
    {
      "lane": 3,
      "time": 74536,
      "type": "tap"
    },
    {
      "lane": 3,
      "time": 75186,
      "type": "tap"
    },
    {
      "lane": 3,
      "time": 75534,
      "type": "tap"
    },
    {
      "lane": 2,
      "time": 75859,
      "type": "tap"
    },
    {
      "lane": 3,
      "time": 75859,
      "type": "tap"
    },
    {
      "lane": 3,
      "time": 76509,
      "type": "tap"
    },
    {
      "lane": 4,
      "time": 77183,
      "type": "tap"
    },
    {
      "lane": 4,
      "time": 77833,
      "type": "tap"
    },
    {
      "lane": 3,
      "time": 78506,
      "type": "tap"
    },
    {
      "lane": 5,
      "time": 79156,
      "type": "tap"
    },
    {
      "lane": 4,
      "time": 79806,
      "type": "tap"
    },
    {
      "lane": 4,
      "time": 80480,
      "type": "tap"
    },
    {
      "lane": 4,
      "time": 81130,
      "type": "tap"
    },
    {
      "lane": 4,
      "time": 81780,
      "type": "tap"
    },
    {
      "lane": 4,
      "time": 82454,
      "type": "tap"
    },
    {
      "lane": 2,
      "time": 82941,
      "type": "tap"
    },
    {
      "lane": 4,
      "time": 83104,
      "type": "tap"
    },
    {
      "lane": 4,
      "time": 83777,
      "type": "tap"
    },
    {
      "lane": 3,
      "time": 84427,
      "type": "tap"
    },
    {
      "lane": 4,
      "time": 85077,
      "type": "tap"
    },
    {
      "lane": 4,
      "time": 86424,
      "type": "tap"
    },
    {
      "lane": 4,
      "time": 87724,
      "type": "tap"
    },
    {
      "lane": 4,
      "time": 89048,
      "type": "tap"
    },
    {
      "lane": 4,
      "time": 90372,
      "type": "tap"
    }
  ]
}