{
  "title": "White world",
  "artist": "Tandess (Tandess)",
  "difficulty": "NORMAL",
  "bpm": 81,
  "audioFile": "songs/white_world_short.mp3",
  "offset": 0,
  "notes": [
    {
      "lane": 0,
      "time": 21989,
      "type": "hold",
      "duration": 1481
    },
    {
      "lane": 1,
      "time": 21989,
      "type": "tap"
    },
    {
      "lane": 0,
      "time": 22569,
      "type": "tap"
    },
    {
      "lane": 2,
      "time": 22755,
      "type": "tap"
    },
    {
      "lane": 3,
      "time": 22755,
      "type": "flick"
    },
    {
      "lane": 0,
      "time": 23103,
      "type": "tap"
    },
    {
      "lane": 0,
      "time": 23498,
      "type": "tap"
    },
    {
      "lane": 0,
      "time": 24241,
      "type": "tap"
    },
    {
      "lane": 0,
      "time": 24613,
      "type": "tap"
    },
    {
      "lane": 2,
      "time": 24984,
      "type": "tap"
    },
    {
      "lane": 3,
      "time": 24984,
      "type": "flick"
    },
    {
      "lane": 0,
      "time": 25704,
      "type": "tap"
    },
    {
      "lane": 3,
      "time": 25704,
      "type": "flick"
    },
    {
      "lane": 0,
      "time": 26447,
      "type": "tap"
    },
    {
      "lane": 0,
      "time": 26819,
      "type": "tap"
    },
    {
      "lane": 2,
      "time": 27190,
      "type": "tap"
    },
    {
      "lane": 3,
      "time": 27190,
      "type": "flick"
    },
    {
      "lane": 0,
      "time": 27933,
      "type": "tap"
    },
    {
      "lane": 0,
      "time": 28119,
      "type": "tap"
    },
    {
      "lane": 0,
      "time": 28676,
      "type": "tap"
    },
    {
      "lane": 2,
      "time": 29419,
      "type": "tap"
    },
    {
      "lane": 3,
      "time": 29419,
      "type": "flick"
    },
    {
      "lane": 0,
      "time": 30162,
      "type": "tap"
    },
    {
      "lane": 0,
      "time": 30882,
      "type": "tap"
    },
    {
      "lane": 0,
      "time": 31277,
      "type": "tap"
    },
    {
      "lane": 2,
      "time": 31648,
      "type": "tap"
    },
    {
      "lane": 0,
      "time": 32391,
      "type": "tap"
    },
    {
      "lane": 0,
      "time": 32554,
      "type": "tap"
    },
    {
      "lane": 0,
      "time": 33111,
      "type": "tap"
    },
    {
      "lane": 2,
      "time": 33854,
      "type": "tap"
    },
    {
      "lane": 0,
      "time": 34226,
      "type": "tap"
    },
    {
      "lane": 0,
      "time": 34597,
      "type": "tap"
    },
    {
      "lane": 0,
      "time": 35340,
      "type": "tap"
    },
    {
      "lane": 0,
      "time": 35712,
      "type": "tap"
    },
    {
      "lane": 2,
      "time": 36083,
      "type": "tap"
    },
    {
      "lane": 0,
      "time": 36826,
      "type": "tap"
    },
    {
      "lane": 5,
      "time": 36826,
      "type": "tap"
    },
    {
      "lane": 0,
      "time": 37569,
      "type": "tap"
    },
    {
      "lane": 2,
      "time": 38312,
      "type": "tap"
    },
    {
      "lane": 0,
      "time": 38661,
      "type": "tap"
    },
    {
      "lane": 0,
      "time": 39055,
      "type": "tap"
    },
    {
      "lane": 2,
      "time": 39845,
      "type": "tap"
    },
    {
      "lane": 2,
      "time": 40216,
      "type": "tap"
    },
    {
      "lane": 3,
      "time": 40518,
      "type": "tap"
    },
    {
      "lane": 4,
      "time": 40913,
      "type": "tap"
    },
    {
      "lane": 2,
      "time": 41308,
      "type": "tap"
    },
    {
      "lane": 2,
      "time": 42051,
      "type": "tap"
    },
    {
      "lane": 2,
      "time": 42283,
      "type": "tap"
    },
    {
      "lane": 1,
      "time": 42747,
      "type": "tap"
    },
    {
      "lane": 4,
      "time": 42747,
      "type": "tap"
    },
    {
      "lane": 4,
      "time": 43514,
      "type": "tap"
    },
    {
      "lane": 2,
      "time": 43932,
      "type": "tap"
    },
    {
      "lane": 2,
      "time": 44234,
      "type": "tap"
    },
    {
      "lane": 3,
      "time": 44907,
      "type": "tap"
    },
    {
      "lane": 2,
      "time": 45673,
      "type": "tap"
    },
    {
      "lane": 2,
      "time": 46439,
      "type": "tap"
    },
    {
      "lane": 5,
      "time": 46857,
      "type": "tap"
    },
    {
      "lane": 3,
      "time": 47206,
      "type": "tap"
    },
    {
      "lane": 3,
      "time": 47949,
      "type": "tap"
    },
    {
      "lane": 3,
      "time": 48715,
      "type": "tap"
    },
    {
      "lane": 2,
      "time": 49086,
      "type": "tap"
    },
    {
      "lane": 3,
      "time": 49435,
      "type": "tap"
    },
    {
      "lane": 1,
      "time": 49806,
      "type": "tap"
    },
    {
      "lane": 1,
      "time": 50155,
      "type": "tap"
    },
    {
      "lane": 2,
      "time": 50898,
      "type": "tap"
    },
    {
      "lane": 2,
      "time": 51641,
      "type": "tap"
    },
    {
      "lane": 4,
      "time": 51966,
      "type": "tap"
    },
    {
      "lane": 4,
      "time": 52360,
      "type": "tap"
    },
    {
      "lane": 4,
      "time": 52825,
      "type": "tap"
    },
    {
      "lane": 4,
      "time": 53173,
      "type": "tap"
    },
    {
      "lane": 2,
      "time": 53870,
      "type": "tap"
    },
    {
      "lane": 2,
      "time": 54822,
      "type": "tap"
    },
    {
      "lane": 3,
      "time": 54822,
      "type": "tap"
    },
    {
      "lane": 5,
      "time": 55658,
      "type": "tap"
    },
    {
      "lane": 3,
      "time": 56424,
      "type": "tap"
    },
    {
      "lane": 5,
      "time": 57167,
      "type": "tap"
    },
    {
      "lane": 4,
      "time": 57794,
      "type": "tap"
    },
    {
      "lane": 2,
      "time": 57957,
      "type": "tap"
    },
    {
      "lane": 2,
      "time": 58305,
      "type": "tap"
    },
    {
      "lane": 2,
      "time": 58630,
      "type": "tap"
    },
    {
      "lane": 3,
      "time": 59071,
      "type": "tap"
    },
    {
      "lane": 2,
      "time": 59326,
      "type": "tap"
    },
    {
      "lane": 2,
      "time": 60046,
      "type": "tap"
    },
    {
      "lane": 5,
      "time": 60371,
      "type": "tap"
    },
    {
      "lane": 3,
      "time": 60580,
      "type": "tap"
    },
    {
      "lane": 3,
      "time": 60789,
      "type": "tap"
    },
    {
      "lane": 5,
      "time": 61509,
      "type": "tap"
    },
    {
      "lane": 3,
      "time": 61741,
      "type": "tap"
    },
    {
      "lane": 1,
      "time": 62275,
      "type": "tap"
    },
    {
      "lane": 2,
      "time": 62438,
      "type": "tap"
    },
    {
      "lane": 5,
      "time": 62693,
      "type": "tap"
    },
    {
      "lane": 2,
      "time": 63042,
      "type": "tap"
    },
    {
      "lane": 1,
      "time": 63808,
      "type": "tap"
    },
    {
      "lane": 2,
      "time": 64551,
      "type": "tap"
    },
    {
      "lane": 2,
      "time": 64946,
      "type": "tap"
    },
    {
      "lane": 2,
      "time": 65271,
      "type": "tap"
    },
    {
      "lane": 4,
      "time": 65991,
      "type": "tap"
    },
    {
      "lane": 3,
      "time": 66710,
      "type": "tap"
    },
    {
      "lane": 5,
      "time": 66989,
      "type": "tap"
    },
    {
      "lane": 4,
      "time": 67198,
      "type": "tap"
    },
    {
      "lane": 5,
      "time": 67407,
      "type": "tap"
    },
    {
      "lane": 2,
      "time": 68104,
      "type": "tap"
    },
    {
      "lane": 2,
      "time": 68870,
      "type": "tap"
    },
    {
      "lane": 4,
      "time": 69729,
      "type": "tap"
    },
    {
      "lane": 5,
      "time": 70519,
      "type": "tap"
    },
    {
      "lane": 4,
      "time": 70890,
      "type": "tap"
    },
    {
      "lane": 3,
      "time": 71238,
      "type": "tap"
    },
    {
      "lane": 2,
      "time": 71958,
      "type": "tap"
    },
    {
      "lane": 2,
      "time": 72701,
      "type": "tap"
    },
    {
      "lane": 3,
      "time": 72701,
      "type": "tap"
    },
    {
      "lane": 0,
      "time": 73421,
      "type": "tap"
    },
    {
      "lane": 1,
      "time": 73746,
      "type": "tap"
    },
    {
      "lane": 2,
      "time": 74141,
      "type": "tap"
    },
    {
      "lane": 4,
      "time": 74861,
      "type": "tap"
    },
    {
      "lane": 2,
      "time": 75627,
      "type": "tap"
    },
    {
      "lane": 4,
      "time": 75998,
      "type": "tap"
    },
    {
      "lane": 3,
      "time": 76393,
      "type": "tap"
    },
    {
      "lane": 5,
      "time": 77136,
      "type": "tap"
    },
    {
      "lane": 3,
      "time": 77856,
      "type": "tap"
    },
    {
      "lane": 4,
      "time": 78135,
      "type": "tap"
    },
    {
      "lane": 2,
      "time": 78599,
      "type": "tap"
    },
    {
      "lane": 4,
      "time": 79342,
      "type": "tap"
    },
    {
      "lane": 2,
      "time": 80062,
      "type": "tap"
    },
    {
      "lane": 5,
      "time": 80480,
      "type": "tap"
    },
    {
      "lane": 3,
      "time": 80782,
      "type": "tap"
    },
    {
      "lane": 5,
      "time": 81548,
      "type": "tap"
    },
    {
      "lane": 3,
      "time": 82291,
      "type": "tap"
    },
    {
      "lane": 4,
      "time": 82523,
      "type": "tap"
    },
    {
      "lane": 3,
      "time": 83080,
      "type": "tap"
    },
    {
      "lane": 1,
      "time": 83870,
      "type": "tap"
    },
    {
      "lane": 1,
      "time": 84567,
      "type": "tap"
    },
    {
      "lane": 4,
      "time": 84567,
      "type": "tap"
    },
    {
      "lane": 2,
      "time": 84961,
      "type": "tap"
    },
    {
      "lane": 1,
      "time": 85240,
      "type": "tap"
    },
    {
      "lane": 1,
      "time": 85913,
      "type": "tap"
    },
    {
      "lane": 1,
      "time": 86610,
      "type": "tap"
    },
    {
      "lane": 2,
      "time": 87190,
      "type": "tap"
    },
    {
      "lane": 4,
      "time": 87957,
      "type": "tap"
    },
    {
      "lane": 2,
      "time": 88677,
      "type": "tap"
    },
    {
      "lane": 0,
      "time": 89048,
      "type": "tap"
    },
    {
      "lane": 2,
      "time": 89420,
      "type": "tap"
    },
    {
      "lane": 0,
      "time": 90139,
      "type": "tap"
    },
    {
      "lane": 5,
      "time": 90139,
      "type": "tap"
    },
    {
      "lane": 0,
      "time": 90882,
      "type": "tap"
    },
    {
      "lane": 0,
      "time": 91463,
      "type": "tap"
    },
    {
      "lane": 2,
      "time": 91625,
      "type": "tap"
    },
    {
      "lane": 0,
      "time": 92392,
      "type": "tap"
    },
    {
      "lane": 0,
      "time": 93112,
      "type": "tap"
    },
    {
      "lane": 0,
      "time": 93483,
      "type": "tap"
    },
    {
      "lane": 2,
      "time": 93878,
      "type": "tap"
    },
    {
      "lane": 0,
      "time": 94621,
      "type": "tap"
    },
    {
      "lane": 0,
      "time": 94783,
      "type": "tap"
    },
    {
      "lane": 0,
      "time": 95341,
      "type": "tap"
    },
    {
      "lane": 2,
      "time": 96084,
      "type": "tap"
    },
    {
      "lane": 0,
      "time": 96827,
      "type": "tap"
    },
    {
      "lane": 0,
      "time": 97547,
      "type": "tap"
    },
    {
      "lane": 0,
      "time": 98127,
      "type": "tap"
    },
    {
      "lane": 2,
      "time": 98313,
      "type": "tap"
    },
    {
      "lane": 0,
      "time": 99056,
      "type": "tap"
    },
    {
      "lane": 0,
      "time": 99799,
      "type": "tap"
    },
    {
      "lane": 2,
      "time": 100542,
      "type": "tap"
    }
  ]
}